App/__init__.py
App/admin.py
App/apps.py
App/models.py
App/tests.py
App/views.py
App/migrations/__init__.py
Project/__init__.py
Project/asgi.py
Project/settings.py
Project/urls.py
Project/wsgi.py
InsightApps-0.1.0.dist-info/LICENSE
InsightApps-0.1.0.dist-info/METADATA
InsightApps-0.1.0.dist-info/WHEEL
InsightApps-0.1.0.dist-info/top_level.txt
InsightApps-0.1.0.dist-info/RECORD
